discordtextsanitizer/__init__.py
discordtextsanitizer/_sanitizers.py
discordtextsanitizer/py.typed
discord_text_sanitizer-0.0.10.dist-info/LICENSE
discord_text_sanitizer-0.0.10.dist-info/METADATA
discord_text_sanitizer-0.0.10.dist-info/WHEEL
discord_text_sanitizer-0.0.10.dist-info/top_level.txt
discord_text_sanitizer-0.0.10.dist-info/RECORD
