Metadata-Version: 2.1
Name: discord-text-sanitizer
Version: 0.0.10
Summary: Text Sanitization For Discord
Home-page: https://github.com/mikeshardmind/discord-text-sanitizer
Author: mikeshardmind
Author-email: michael@michaelhall.tech
License: MIT
Platform: UNKNOWN
Classifier: Intended Audience :: Developers
Classifier: License :: OSI Approved :: MIT License
Classifier: Operating System :: OS Independent
Classifier: Programming Language :: Python :: 3 :: Only
Classifier: Programming Language :: Python :: 3.6
Classifier: Programming Language :: Python :: 3.7
Classifier: Programming Language :: Python :: 3.8
Classifier: Topic :: Communications :: Chat
Requires-Python: >=3.6
Requires-Dist: ftfy
Requires-Dist: python-bidi
